{
"type": "FeatureCollection",
"name": "MUFA (#4)",
"crs": { "type": "name", "properties": { "name": "urn:ogc:def:crs:OGC:1.3:CRS84" } },
"features": [
{ "type": "Feature", "properties": { "Field_1": "Secondary splice closure", "Type": "SEC_SC", "Country": null }, "geometry": { "type": "Point", "coordinates": [ -89.250184027075505, 13.703539926255701 ] } },
{ "type": "Feature", "properties": { "Field_1": "Secondary splice closure", "Type": "SEC_SC", "Country": null }, "geometry": { "type": "Point", "coordinates": [ -89.241244121826995, 13.701824609192 ] } },
{ "type": "Feature", "properties": { "Field_1": "Secondary splice closure", "Type": "SEC_SC", "Country": "El Sal" }, "geometry": { "type": "Point", "coordinates": [ -89.243561540799703, 13.702972098069599 ] } }
]
}
